{
  "annotations": {
    "list": []
  },
  "editable": true,
  "gnetId": null,
  "graphTooltip": 0,
  "id": null,
  "links": [],
  "panels": [
    {
      "datasource": "Prometheus",
      "fieldConfig": {
        "defaults": {
          "color": {
            "mode": "thresholds"
          },
          "mappings": [],
          "thresholds": {
            "mode": "absolute",
            "steps": [
              {
                "color": "green",
                "value": null
              },
              {
                "color": "yellow",
                "value": 99.0
              },
              {
                "color": "red",
                "value": 95.0
              }
            ]
          },
          "unit": "percent"
        }
      },
      "gridPos": {
        "h": 4,
        "w": 6,
        "x": 0,
        "y": 0
      },
      "id": 1,
      "options": {
        "colorMode": "value",
        "graphMode": "none",
        "justifyMode": "auto",
        "orientation": "auto",
        "reduceOptions": {
          "values": false,
          "calcs": ["lastNotNull"],
          "fields": ""
        },
        "text": {},
        "textMode": "auto"
      },
      "pluginVersion": "8.0.0",
      "targets": [
        {
          "expr": "(count(container_memory_usage_bytes{name=~\"lianel-energy-service|lianel-profile-service|dc-airflow.*\"} > 0) / count(container_memory_usage_bytes{name=~\"lianel-energy-service|lianel-profile-service|dc-airflow.*\"}) * 100) OR vector(100)",
          "refId": "A"
        }
      ],
      "title": "Service Uptime SLA",
      "description": "Target: >99.5%",
      "type": "stat"
    },
    {
      "datasource": {
        "type": "postgres",
        "uid": "postgres-airflow"
      },
      "fieldConfig": {
        "defaults": {
          "color": {
            "mode": "thresholds"
          },
          "mappings": [],
          "thresholds": {
            "mode": "absolute",
            "steps": [
              {
                "color": "green",
                "value": null
              },
              {
                "color": "yellow",
                "value": 95.0
              },
              {
                "color": "red",
                "value": 90.0
              }
            ]
          },
          "unit": "percent"
        }
      },
      "gridPos": {
        "h": 4,
        "w": 6,
        "x": 6,
        "y": 0
      },
      "id": 2,
      "options": {
        "colorMode": "value",
        "graphMode": "none",
        "justifyMode": "auto",
        "orientation": "auto",
        "reduceOptions": {
          "values": false,
          "calcs": ["lastNotNull"],
          "fields": ""
        },
        "text": {},
        "textMode": "auto"
      },
      "pluginVersion": "8.0.0",
      "targets": [
        {
          "datasource": {
            "type": "postgres",
            "uid": "postgres-airflow"
          },
          "editorMode": "code",
          "format": "table",
          "rawQuery": true,
          "rawSql": "SELECT CASE WHEN total > 0 THEN (success::float / total::float * 100) ELSE 0 END as success_rate FROM (SELECT COUNT(*) FILTER (WHERE state = 'success') as success, COUNT(*) FILTER (WHERE end_date IS NOT NULL) as total FROM public.dag_run WHERE end_date IS NOT NULL AND end_date > NOW() - INTERVAL '7 days') subq;",
          "refId": "A",
          "sql": {
            "columns": [
              {
                "parameters": [],
                "type": "function"
              }
            ],
            "groupBy": [
              {
                "property": {
                  "type": "string"
                },
                "type": "groupBy"
              }
            ],
            "limit": 50
          }
        }
      ],
      "title": "DAG Success Rate SLA",
      "description": "Target: >95% (7 days)",
      "type": "stat"
    },
    {
      "datasource": {
        "type": "postgres",
        "uid": "postgres-airflow"
      },
      "fieldConfig": {
        "defaults": {
          "color": {
            "mode": "thresholds"
          },
          "mappings": [],
          "thresholds": {
            "mode": "absolute",
            "steps": [
              {
                "color": "green",
                "value": null
              },
              {
                "color": "yellow",
                "value": 7200
              },
              {
                "color": "red",
                "value": 10800
              }
            ]
          },
          "unit": "s"
        }
      },
      "gridPos": {
        "h": 4,
        "w": 6,
        "x": 12,
        "y": 0
      },
      "id": 3,
      "options": {
        "colorMode": "value",
        "graphMode": "none",
        "justifyMode": "auto",
        "orientation": "auto",
        "reduceOptions": {
          "values": false,
          "calcs": ["mean"],
          "fields": ""
        },
        "text": {},
        "textMode": "auto"
      },
      "pluginVersion": "8.0.0",
      "targets": [
        {
          "datasource": {
            "type": "postgres",
            "uid": "postgres-airflow"
          },
          "editorMode": "code",
          "format": "table",
          "rawQuery": true,
          "rawSql": "SELECT AVG(EXTRACT(EPOCH FROM (end_date - start_date))) as avg_duration FROM public.dag_run WHERE state = 'success' AND end_date IS NOT NULL AND start_date IS NOT NULL AND end_date > NOW() - INTERVAL '7 days';",
          "refId": "A",
          "sql": {
            "columns": [
              {
                "parameters": [],
                "type": "function"
              }
            ],
            "groupBy": [
              {
                "property": {
                  "type": "string"
                },
                "type": "groupBy"
              }
            ],
            "limit": 50
          }
        }
      ],
      "title": "Avg DAG Duration",
      "description": "Target: <2 hours (7200s)",
      "type": "stat"
    },
    {
      "datasource": {
        "type": "postgres",
        "uid": "postgres-airflow"
      },
      "fieldConfig": {
        "defaults": {
          "color": {
            "mode": "thresholds"
          },
          "mappings": [],
          "thresholds": {
            "mode": "absolute",
            "steps": [
              {
                "color": "green",
                "value": null
              },
              {
                "color": "yellow",
                "value": 86400
              },
              {
                "color": "red",
                "value": 172800
              }
            ]
          },
          "unit": "s"
        }
      },
      "gridPos": {
        "h": 4,
        "w": 6,
        "x": 18,
        "y": 0
      },
      "id": 4,
      "options": {
        "colorMode": "value",
        "graphMode": "none",
        "justifyMode": "auto",
        "orientation": "auto",
        "reduceOptions": {
          "values": false,
          "calcs": ["lastNotNull"],
          "fields": ""
        },
        "text": {},
        "textMode": "auto"
      },
      "pluginVersion": "8.0.0",
      "targets": [
        {
          "datasource": {
            "type": "postgres",
            "uid": "postgres-airflow"
          },
          "editorMode": "code",
          "format": "table",
          "rawQuery": true,
          "rawSql": "SELECT EXTRACT(EPOCH FROM (NOW() - MAX(ingestion_date))) as data_age FROM meta_ingestion_log WHERE ingestion_date IS NOT NULL;",
          "refId": "A",
          "sql": {
            "columns": [
              {
                "parameters": [],
                "type": "function"
              }
            ],
            "groupBy": [
              {
                "property": {
                  "type": "string"
                },
                "type": "groupBy"
              }
            ],
            "limit": 50
          }
        }
      ],
      "title": "Data Freshness",
      "description": "Target: <24 hours (86400s)",
      "type": "stat"
    },
    {
      "datasource": "Prometheus",
      "fieldConfig": {
        "defaults": {
          "color": {
            "mode": "thresholds"
          },
          "mappings": [],
          "thresholds": {
            "mode": "absolute",
            "steps": [
              {
                "color": "green",
                "value": null
              },
              {
                "color": "yellow",
                "value": 0.5
              },
              {
                "color": "red",
                "value": 1.0
              }
            ]
          },
          "unit": "s"
        }
      },
      "gridPos": {
        "h": 4,
        "w": 6,
        "x": 0,
        "y": 4
      },
      "id": 5,
      "options": {
        "colorMode": "value",
        "graphMode": "none",
        "justifyMode": "auto",
        "orientation": "auto",
        "reduceOptions": {
          "values": false,
          "calcs": ["lastNotNull"],
          "fields": ""
        },
        "text": {},
        "textMode": "auto"
      },
      "pluginVersion": "8.0.0",
      "targets": [
        {
          "expr": "histogram_quantile(0.95, rate(http_request_duration_seconds_bucket[5m]))",
          "refId": "A"
        }
      ],
      "title": "API Response Time (p95)",
      "description": "Target: <500ms (0.5s)",
      "type": "stat"
    },
    {
      "datasource": {
        "type": "postgres",
        "uid": "postgres-airflow"
      },
      "fieldConfig": {
        "defaults": {
          "color": {
            "mode": "thresholds"
          },
          "mappings": [],
          "thresholds": {
            "mode": "absolute",
            "steps": [
              {
                "color": "green",
                "value": null
              },
              {
                "color": "yellow",
                "value": 5
              },
              {
                "color": "red",
                "value": 10
              }
            ]
          },
          "unit": "s"
        }
      },
      "gridPos": {
        "h": 4,
        "w": 6,
        "x": 6,
        "y": 4
      },
      "id": 6,
      "options": {
        "colorMode": "value",
        "graphMode": "none",
        "justifyMode": "auto",
        "orientation": "auto",
        "reduceOptions": {
          "values": false,
          "calcs": ["mean"],
          "fields": ""
        },
        "text": {},
        "textMode": "auto"
      },
      "pluginVersion": "8.0.0",
      "targets": [
        {
          "datasource": {
            "type": "postgres",
            "uid": "postgres-airflow"
          },
          "editorMode": "code",
          "format": "table",
          "rawQuery": true,
          "rawSql": "SELECT AVG(EXTRACT(EPOCH FROM (end_date - start_date))) as avg_query_time FROM (SELECT start_date, end_date FROM public.dag_run WHERE state = 'success' AND end_date IS NOT NULL AND start_date IS NOT NULL AND end_date > NOW() - INTERVAL '7 days' LIMIT 100) subq;",
          "refId": "A",
          "sql": {
            "columns": [
              {
                "parameters": [],
                "type": "function"
              }
            ],
            "groupBy": [
              {
                "property": {
                  "type": "string"
                },
                "type": "groupBy"
              }
            ],
            "limit": 50
          }
        }
      ],
      "title": "Query Performance",
      "description": "Target: <5s",
      "type": "stat"
    },
    {
      "datasource": "Prometheus",
      "fieldConfig": {
        "defaults": {
          "color": {
            "mode": "palette-classic"
          },
          "custom": {
            "axisLabel": "",
            "axisPlacement": "auto",
            "barAlignment": 0,
            "drawStyle": "line",
            "fillOpacity": 10,
            "gradientMode": "none",
            "hideFrom": {
              "tooltip": false,
              "viz": false,
              "legend": false
            },
            "lineInterpolation": "linear",
            "lineWidth": 1,
            "pointSize": 5,
            "scaleDistribution": {
              "type": "linear"
            },
            "showPoints": "never",
            "spanNulls": true
          },
          "mappings": [],
          "thresholds": {
            "mode": "absolute",
            "steps": [
              {
                "color": "green",
                "value": null
              },
              {
                "color": "red",
                "value": 0.995
              }
            ]
          },
          "unit": "percent"
        }
      },
      "gridPos": {
        "h": 8,
        "w": 12,
        "x": 0,
        "y": 8
      },
      "id": 7,
      "options": {
        "legend": {
          "calcs": ["mean", "min", "max"],
          "displayMode": "table",
          "placement": "bottom"
        },
        "tooltip": {
          "mode": "multi"
        }
      },
      "pluginVersion": "8.0.0",
      "targets": [
        {
          "expr": "(count(container_memory_usage_bytes{name=~\"lianel-energy-service|lianel-profile-service|dc-airflow.*\"} > 0) / count(container_memory_usage_bytes{name=~\"lianel-energy-service|lianel-profile-service|dc-airflow.*\"}) * 100) OR vector(100)",
          "legendFormat": "Service Uptime",
          "refId": "A"
        }
      ],
      "title": "Service Uptime SLA Trend (7 days)",
      "type": "timeseries"
    },
    {
      "datasource": {
        "type": "postgres",
        "uid": "postgres-airflow"
      },
      "fieldConfig": {
        "defaults": {
          "color": {
            "mode": "palette-classic"
          },
          "custom": {
            "axisLabel": "",
            "axisPlacement": "auto",
            "barAlignment": 0,
            "drawStyle": "line",
            "fillOpacity": 10,
            "gradientMode": "none",
            "hideFrom": {
              "tooltip": false,
              "viz": false,
              "legend": false
            },
            "lineInterpolation": "linear",
            "lineWidth": 1,
            "pointSize": 5,
            "scaleDistribution": {
              "type": "linear"
            },
            "showPoints": "never",
            "spanNulls": true
          },
          "mappings": [],
          "thresholds": {
            "mode": "absolute",
            "steps": [
              {
                "color": "green",
                "value": null
              },
              {
                "color": "red",
                "value": 95
              }
            ]
          },
          "unit": "percent"
        }
      },
      "gridPos": {
        "h": 8,
        "w": 12,
        "x": 12,
        "y": 8
      },
      "id": 8,
      "options": {
        "legend": {
          "calcs": ["mean", "min", "max"],
          "displayMode": "table",
          "placement": "bottom"
        },
        "tooltip": {
          "mode": "multi"
        }
      },
      "pluginVersion": "8.0.0",
      "targets": [
        {
          "datasource": {
            "type": "postgres",
            "uid": "postgres-airflow"
          },
          "editorMode": "code",
          "format": "time_series",
          "rawQuery": true,
          "rawSql": "SELECT date_trunc('hour', end_date)::timestamp as time, (COUNT(*) FILTER (WHERE state = 'success')::float / NULLIF(COUNT(*), 0)::float * 100) as success_rate FROM public.dag_run WHERE end_date IS NOT NULL AND end_date > NOW() - INTERVAL '7 days' GROUP BY time ORDER BY time;",
          "refId": "A",
          "sql": {
            "columns": [
              {
                "parameters": [],
                "type": "function"
              }
            ],
            "groupBy": [
              {
                "property": {
                  "type": "string"
                },
                "type": "groupBy"
              }
            ],
            "limit": 50
          }
        }
      ],
      "title": "DAG Success Rate Trend (7 days)",
      "type": "timeseries"
    },
    {
      "datasource": {
        "type": "postgres",
        "uid": "postgres-airflow"
      },
      "fieldConfig": {
        "defaults": {
          "color": {
            "mode": "thresholds"
          },
          "mappings": [],
          "thresholds": {
            "mode": "absolute",
            "steps": [
              {
                "color": "green",
                "value": null
              }
            ]
          },
          "unit": "short"
        }
      },
      "gridPos": {
        "h": 8,
        "w": 24,
        "x": 0,
        "y": 16
      },
      "id": 9,
      "options": {
        "displayMode": "list",
        "footer": {
          "countRows": false,
          "fields": "",
          "reducer": ["sum"],
          "show": false
        },
        "showHeader": true
      },
      "pluginVersion": "8.0.0",
      "targets": [
        {
          "datasource": {
            "type": "postgres",
            "uid": "postgres-airflow"
          },
          "editorMode": "code",
          "format": "table",
          "rawQuery": true,
          "rawSql": "SELECT dag_id, COUNT(*) FILTER (WHERE state = 'success') as success_count, COUNT(*) FILTER (WHERE state = 'failed') as failed_count, COUNT(*) as total_runs, CASE WHEN COUNT(*) > 0 THEN (COUNT(*) FILTER (WHERE state = 'success')::float / COUNT(*)::float * 100) ELSE 0 END as success_rate, AVG(EXTRACT(EPOCH FROM (end_date - start_date))) FILTER (WHERE end_date IS NOT NULL AND start_date IS NOT NULL) as avg_duration_seconds FROM public.dag_run WHERE end_date IS NOT NULL AND end_date > NOW() - INTERVAL '7 days' GROUP BY dag_id ORDER BY success_rate ASC;",
          "refId": "A",
          "sql": {
            "columns": [
              {
                "parameters": [],
                "type": "function"
              }
            ],
            "groupBy": [
              {
                "property": {
                  "type": "string"
                },
                "type": "groupBy"
              }
            ],
            "limit": 50
          }
        }
      ],
      "title": "SLA Compliance by DAG (7 days)",
      "type": "table"
    }
  ],
  "refresh": "1m",
  "schemaVersion": 27,
  "style": "dark",
  "tags": ["sla", "monitoring", "operational"],
  "templating": {
    "list": []
  },
  "time": {
    "from": "now-7d",
    "to": "now"
  },
  "timepicker": {},
  "timezone": "",
  "title": "SLA Monitoring",
  "uid": "sla-monitoring",
  "version": 1
}
